youte/__init__.py
youte/_logging.py
youte/_typing.py
youte/cli.py
youte/collector.py
youte/common.py
youte/config.py
youte/database.py
youte/exceptions.py
youte/parser.py
youte/resources.py
youte/utilities.py
youte/version.py
youte-2.6.1.dist-info/LICENCE
youte-2.6.1.dist-info/METADATA
youte-2.6.1.dist-info/WHEEL
youte-2.6.1.dist-info/entry_points.txt
youte-2.6.1.dist-info/top_level.txt
youte-2.6.1.dist-info/RECORD
