Metadata-Version: 2.1
Name: youte
Version: 2.6.1
Summary: Command-line tool to collect video metadata and comments from Youtube API
Home-page: https://github.com/QUT-Digital-Observatory/youte
Author: Digital Observatory
Author-email: digitalobservatory@qut.edu.au
Project-URL: Bug Tracker, https://github.com/QUT-Digital-Observatory/youte/issues
Classifier: Development Status :: 5 - Production/Stable
Classifier: Programming Language :: Python :: 3.8
Classifier: Programming Language :: Python :: 3.9
Classifier: Programming Language :: Python :: 3.10
Requires-Python: >=3.8
License-File: LICENCE
Requires-Dist: click>=8.0.3
Requires-Dist: requests>=2.27.1
Requires-Dist: python-dateutil>=2.8.2
Requires-Dist: configobj>=5.0.6
Requires-Dist: typing-extensions>=4.5.0
Requires-Dist: SQLAlchemy>=2.0.7
Requires-Dist: pydantic>=1.10.7
Requires-Dist: click-log>=0.4.0
